pyREyes/REyes.py
pyREyes/append_targets_nav.py
pyREyes/create_final_targets_nav.py
pyREyes/dif_map.py
pyREyes/eucentricity.py
pyREyes/grid_squares.py
pyREyes/manual_squares.py
pyREyes/mnt_maps_targets.py
pyREyes/write_sorted_targets_nav.py
pyREyes/config/filtering_options.json
pyREyes/config/microscope_configs.json
pyREyes/docs/README_FULL.md
pyREyes/docs/modules/diffraction-map.md
pyREyes/docs/modules/eucentricity.md
pyREyes/docs/modules/final-targets.md
pyREyes/docs/modules/grid-squares.md
pyREyes/docs/modules/manual-squares.md
pyREyes/docs/modules/map-plotter.md
pyREyes/docs/modules/monitor.md
pyREyes/docs/modules/navigation.md
pyREyes/docs/modules/targets.md
pyREyes/lib/REyes_errors.py
pyREyes/lib/REyes_logging.py
pyREyes/lib/REyes_microscope_configurations.py
pyREyes/lib/REyes_utils.py
pyREyes/lib/__init__.py
pyREyes/lib/diffraction/DiffractionDataProcessor.py
pyREyes/lib/grid_processing/CentroidProcessor.py
pyREyes/lib/grid_processing/GridProcessor.py
pyREyes/lib/grid_processing/filtering_options.py
pyREyes/lib/image_processing/CartImage.py
pyREyes/lib/image_processing/CartImage_utils.py
pyREyes/lib/image_processing/PlottingManager.py
pyREyes/lib/image_processing/__init__.py
pyREyes/lib/image_processing/image_processor.py
pyREyes/lib/ui/REyes_ui.py
pyREyes/lib/ui/__init__.py
pyreyes-3.4.0.dist-info/METADATA
pyreyes-3.4.0.dist-info/WHEEL
pyreyes-3.4.0.dist-info/entry_points.txt
pyreyes-3.4.0.dist-info/licenses/LICENSE
pyreyes-3.4.0.dist-info/RECORD
