Metadata-Version: 2.4
Name: pyREyes
Version: 3.4.0
Summary: Automated MicroED diffraction data collection and analysis package
Project-URL: Homepage, https://github.com/theNelsonLab/REyes
Project-URL: Issues, https://github.com/theNelsonLab/REyes/issues
Project-URL: Documentation, https://github.com/theNelsonLab/REyes/tree/main/src/pyREyes/docs
Author-email: Dmitry Eremin <eremin@caltech.edu>, Hongyu Zhang <hzhang7@caltech.edu>
License-File: LICENSE
Classifier: Operating System :: OS Independent
Classifier: Programming Language :: Python :: 3
Classifier: Programming Language :: Python :: 3.10
Requires-Python: >=3.10
Requires-Dist: hyperspy==2.3.0
Requires-Dist: matplotlib==3.10.3
Requires-Dist: numba==0.61.2
Requires-Dist: numpy==2.2.6
Requires-Dist: pandas==2.2.3
Requires-Dist: psutil==7.0.0
Requires-Dist: pyautoprocess>=0.1.1
Requires-Dist: scikit-image==0.25.2
Requires-Dist: scikit-learn==1.6.1
Requires-Dist: scipy==1.15.3
Requires-Dist: shapely==2.1.1
